Workbook

Sheet Guide
A1: Chapter 3: Two Lives, Excel cross-check
A2: Part of The Odds of a Lifetime. This workbook rebuilds the Chapter 3 calculations independently in spreadsheet formulas.
A4: Sheets
A5: Assumptions: the couple, the pension and the Makeham mortality parameters (SOA Standard Ultimate Life Table).
A6: Life table: one-year death rates for each life, survival of each life, the joint-life and last-survivor statuses, and the annuities.
A7: Cross-check: R calculator results side by side with Excel, plus a check against the published SOA table.
A8: Experience: the SQL couples study from R, compared with the model.
A10: Legend
A11: Blue text on yellow = input you can change
A12: Black text = formula
A13: Green text = value pulled from another sheet
A15: Illustrative assumptions only, not calibrated to real data and not a pricing basis.

Sheet Assumptions
A1: Assumptions
A2: Two independent lives. Income paid at the start of each year, up to age 120 for the younger life.
A4: Item | B4: Value | C4: Note
A5: Age of first life (x) | B5: 65 | C5: Between 50 and 85.
A6: Age of second life (y) | B6: 62 | C6: Between 50 and 85.
A7: Annual income | B7: 20000 | C7: Paid at the start of each year.
A8: Survivor's share after the first death | B8: 0.6 | C8: Share of the income paid to whoever survives.
A9: Annual interest rate i | B9: 0.05 | C9: Effective rate.
A10: Makeham A | B10: 0.00022 | C10: SOA Standard Ultimate Life Table.
A11: Makeham B | B11: 2.7e-06 | C11: SOA Standard Ultimate Life Table.
A12: Makeham c | B12: 1.124 | C12: SOA Standard Ultimate Life Table.
A14: Years of payments n = 120 - younger age | B14: =120-MIN(B5,B6) -> 58
A15: Ages within range? | B15: =IF(AND(B5>=50,B5<=85,B6>=50,B6<=85),"OK","Ages must be 50 to 85") -> OK

Sheet Life table
A1: Life table for the couple
A2: Makeham: q = 1 - exp(-A - B c^age (c - 1) / ln c). Joint life: kp_xy = kp_x kp_y. Last survivor: kp_x + kp_y - kp_xy. Annuities sum v^k kp for k = 0 to n - 1.
A7: Year k | B7: Within payments (1/0) | C7: Age of x | D7: q for x | E7: Age of y | F7: q for y | G7: kp_x | H7: kp_y | I7: kp_xy (both alive) | J7: kp last survivor (at least one alive) | K7: Discount v^k | L7: Annuity term x | M7: Annuity term y | N7: Annuity term joint | O7: Annuity term last survivor | P7: (x) dies first in year k+1 | R7: Results
A8: 0 | B8: =IF(A8<Assumptions!$B$14,1,0) -> 1 | C8: =Assumptions!$B$5+A8 -> 65 | D8: =1-EXP(-Assumptions!$B$10-Assumptions!$B$11*Assumptions!$B$12^C8*(Assumptions!$B$12-1)/LN(Assumptions!$B$12)) -> 0.005914652 | E8: =Assumptions!$B$6+A8 -> 62 | F8: =1-EXP(-Assumptions!$B$10-Assumptions!$B$11*Assumptions!$B$12^E8*(Assumptions!$B$12-1)/LN(Assumptions!$B$12)) -> 0.0042336 | G8: 1 | H8: 1 | I8: =G8*H8 -> 1 | J8: =G8+H8-I8 -> 1 | K8: =(1+Assumptions!$B$9)^-A8 -> 1 | L8: =B8*K8*G8 -> 1 | M8: =B8*K8*H8 -> 1 | N8: =B8*K8*I8 -> 1 | O8: =B8*K8*J8 -> 1 | P8: =B8*I8*D8*(1-F8/2) -> 0.0059021319 | R8: Annuity factor, x | S8: =SUM(L8:L78) -> 13.54979
A9: 1 | B9: =IF(A9<Assumptions!$B$14,1,0) -> 1 | C9: =Assumptions!$B$5+A9 -> 66 | D9: =1-EXP(-Assumptions!$B$10-Assumptions!$B$11*Assumptions!$B$12^C9*(Assumptions!$B$12-1)/LN(Assumptions!$B$12)) -> 0.0066185277 | E9: =Assumptions!$B$6+A9 -> 63 | F9: =1-EXP(-Assumptions!$B$10-Assumptions!$B$11*Assumptions!$B$12^E9*(Assumptions!$B$12-1)/LN(Assumptions!$B$12)) -> 0.0047301652 | G9: =G8*(1-D8) -> 0.99408535 | H9: =H8*(1-F8) -> 0.9957664 | I9: =G9*H9 -> 0.98987679 | J9: =G9+H9-I9 -> 0.99997496 | K9: =(1+Assumptions!$B$9)^-A9 -> 0.95238095 | L9: =B9*K9*G9 -> 0.94674795 | M9: =B9*K9*H9 -> 0.94834895 | N9: =B9*K9*I9 -> 0.9427398 | O9: =B9*K9*J9 -> 0.9523571 | P9: =B9*I9*D9*(1-F9/2) -> 0.006536032 | R9: Annuity factor, y | S9: =SUM(M8:M78) -> 14.386058
A10: 2 | B10: =IF(A10<Assumptions!$B$14,1,0) -> 1 | C10: =Assumptions!$B$5+A10 -> 67 | D10: =1-EXP(-Assumptions!$B$10-Assumptions!$B$11*Assumptions!$B$12^C10*(Assumptions!$B$12-1)/LN(Assumptions!$B$12)) -> 0.007409089 | E10: =Assumptions!$B$6+A10 -> 64 | F10: =1-EXP(-Assumptions!$B$10-Assumptions!$B$11*Assumptions!$B$12^E10*(Assumptions!$B$12-1)/LN(Assumptions!$B$12)) -> 0.0052880089 | G10: =G9*(1-D9) -> 0.98750597 | H10: =H9*(1-F9) -> 0.99105626 | I10: =G10*H10 -> 0.97867397 | J10: =G10+H10-I10 -> 0.99988826 | K10: =(1+Assumptions!$B$9)^-A10 -> 0.90702948 | L10: =B10*K10*G10 -> 0.89569702 | M10: =B10*K10*H10 -> 0.89891724 | N10: =B10*K10*I10 -> 0.88768614 | O10: =B10*K10*J10 -> 0.90692812 | P10: =B10*I10*D10*(1-F10/2) -> 0.0072319107 | R10: Annuity factor, joint life | S10: =SUM(N8:N78) -> 12.128319
A11: 3 | B11: =IF(A11<Assumptions!$B$14,1,0) -> 1 | C11: =Assumptions!$B$5+A11 -> 68 | D11: =1-EXP(-Assumptions!$B$10-Assumptions!$B$11*Assumptions!$B$12^C11*(Assumptions!$B$12-1)/LN(Assumptions!$B$12)) -> 0.008296929 | E11: =Assumptions!$B$6+A11 -> 65 | F11: =1-EXP(-Assumptions!$B$10-Assumptions!$B$11*Assumptions!$B$12^E11*(Assumptions!$B$12-1)/LN(Assumptions!$B$12)) -> 0.005914652 | G11: =G10*(1-D10) -> 0.98018945 | H11: =H10*(1-F10) -> 0.98581555 | I11: =G11*H11 -> 0.96628599 | J11: =G11+H11-I11 -> 0.999719 | K11: =(1+Assumptions!$B$9)^-A11 -> 0.8638376 | L11: =B11*K11*G11 -> 0.8467245 | M11: =B11*K11*H11 -> 0.85158453 | N11: =B11*K11*I11 -> 0.83471417 | O11: =B11*K11*J11 -> 0.86359486 | P11: =B11*I11*D11*(1-F11/2) -> 0.0079934968 | R11: Annuity factor, last survivor | S11: =SUM(O8:O78) -> 15.807528
A12: 4 | B12: =IF(A12<Assumptions!$B$14,1,0) -> 1 | C12: =Assumptions!$B$5+A12 -> 69 | D12: =1-EXP(-Assumptions!$B$10-Assumptions!$B$11*Assumptions!$B$12^C12*(Assumptions!$B$12-1)/LN(Assumptions!$B$12)) -> 0.0092939131 | E12: =Assumptions!$B$6+A12 -> 66 | F12: =1-EXP(-Assumptions!$B$10-Assumptions!$B$11*Assumptions!$B$12^E12*(Assumptions!$B$12-1)/LN(Assumptions!$B$12)) -> 0.0066185277 | G12: =G11*(1-D11) -> 0.97205688 | H12: =H11*(1-F11) -> 0.97998479 | I12: =G12*H12 -> 0.95260096 | J12: =G12+H12-I12 -> 0.99944071 | K12: =(1+Assumptions!$B$9)^-A12 -> 0.82270247 | L12: =B12*K12*G12 -> 0.7997136 | M12: =B12*K12*H12 -> 0.80623591 | N12: =B12*K12*I12 -> 0.78370717 | O12: =B12*K12*J12 -> 0.82224235 | P12: =B12*I12*D12*(1-F12/2) -> 0.0088240924 | R12: Reversionary annuity to (y) after (x) dies | S12: =S9-S10 -> 2.2577384
A13: 5 | B13: =IF(A13<Assumptions!$B$14,1,0) -> 1 | C13: =Assumptions!$B$5+A13 -> 70 | D13: =1-EXP(-Assumptions!$B$10-Assumptions!$B$11*Assumptions!$B$12^C13*(Assumptions!$B$12-1)/LN(Assumptions!$B$12)) -> 0.010413327 | E13: =Assumptions!$B$6+A13 -> 67 | F13: =1-EXP(-Assumptions!$B$10-Assumptions!$B$11*Assumptions!$B$12^E13*(Assumptions!$B$12-1)/LN(Assumptions!$B$12)) -> 0.007409089 | G13: =G12*(1-D12) -> 0.96302267 | H13: =H12*(1-F12) -> 0.97349873 | I13: =G13*H13 -> 0.93750135 | J13: =G13+H13-I13 -> 0.99902005 | K13: =(1+Assumptions!$B$9)^-A13 -> 0.78352617 | L13: =B13*K13*G13 -> 0.75455346 | M13: =B13*K13*H13 -> 0.76276173 | N13: =B13*K13*I13 -> 0.73455684 | O13: =B13*K13*J13 -> 0.78275835 | P13: =B13*I13*D13*(1-F13/2) -> 0.0097263425 | R13: Cost of a joint and survivor pension | S13: =Assumptions!$B$7*(Assumptions!$B$8*S11+(1-Assumptions!$B$8)*S10) -> 286716.9
A14: 6 | B14: =IF(A14<Assumptions!$B$14,1,0) -> 1 | C14: =Assumptions!$B$5+A14 -> 71 | D14: =1-EXP(-Assumptions!$B$10-Assumptions!$B$11*Assumptions!$B$12^C14*(Assumptions!$B$12-1)/LN(Assumptions!$B$12)) -> 0.011670038 | E14: =Assumptions!$B$6+A14 -> 68 | F14: =1-EXP(-Assumptions!$B$10-Assumptions!$B$11*Assumptions!$B$12^E14*(Assumptions!$B$12-1)/LN(Assumptions!$B$12)) -> 0.008296929 | G14: =G13*(1-D13) -> 0.9529944 | H14: =H13*(1-F13) -> 0.96628599 | I14: =G14*H14 -> 0.92086514 | J14: =G14+H14-I14 -> 0.99841525 | K14: =(1+Assumptions!$B$9)^-A14 -> 0.7462154 | L14: =B14*K14*G14 -> 0.7111391 | M14: =B14*K14*H14 -> 0.72105749 | N14: =B14*K14*I14 -> 0.68716375 | O14: =B14*K14*J14 -> 0.74503283 | P14: =B14*I14*D14*(1-F14/2) -> 0.01070195 | R14: Cost if income continues in full to the survivor | S14: =Assumptions!$B$7*S11 -> 316150.57
A15: 7 | B15: =IF(A15<Assumptions!$B$14,1,0) -> 1 | C15: =Assumptions!$B$5+A15 -> 72 | D15: =1-EXP(-Assumptions!$B$10-Assumptions!$B$11*Assumptions!$B$12^C15*(Assumptions!$B$12-1)/LN(Assumptions!$B$12)) -> 0.013080677 | E15: =Assumptions!$B$6+A15 -> 69 | F15: =1-EXP(-Assumptions!$B$10-Assumptions!$B$11*Assumptions!$B$12^E15*(Assumptions!$B$12-1)/LN(Assumptions!$B$12)) -> 0.0092939131 | G15: =G14*(1-D14) -> 0.94187292 | H15: =H14*(1-F14) -> 0.95826879 | I15: =G15*H15 -> 0.90256742 | J15: =G15+H15-I15 -> 0.99757429 | K15: =(1+Assumptions!$B$9)^-A15 -> 0.71068133 | L15: =B15*K15*G15 -> 0.6693715 | M15: =B15*K15*H15 -> 0.68102374 | N15: =B15*K15*I15 -> 0.64143782 | O15: =B15*K15*J15 -> 0.70895742 | P15: =B15*I15*D15*(1-F15/2) -> 0.01175133 | R15: Cost if income stops at the first death | S15: =Assumptions!$B$7*S10 -> 242566.39
A16: 8 | B16: =IF(A16<Assumptions!$B$14,1,0) -> 1 | C16: =Assumptions!$B$5+A16 -> 73 | D16: =1-EXP(-Assumptions!$B$10-Assumptions!$B$11*Assumptions!$B$12^C16*(Assumptions!$B$12-1)/LN(Assumptions!$B$12)) -> 0.014663832 | E16: =Assumptions!$B$6+A16 -> 70 | F16: =1-EXP(-Assumptions!$B$10-Assumptions!$B$11*Assumptions!$B$12^E16*(Assumptions!$B$12-1)/LN(Assumptions!$B$12)) -> 0.010413327 | G16: =G15*(1-D15) -> 0.92955259 | H16: =H15*(1-F15) -> 0.94936272 | I16: =G16*H16 -> 0.88248257 | J16: =G16+H16-I16 -> 0.99643273 | K16: =(1+Assumptions!$B$9)^-A16 -> 0.67683936 | L16: =B16*K16*G16 -> 0.62915778 | M16: =B16*K16*H16 -> 0.64256606 | N16: =B16*K16*I16 -> 0.59729894 | O16: =B16*K16*J16 -> 0.6744249 | P16: =B16*I16*D16*(1-F16/2) -> 0.012873199 | R16: Cost of income to (y) only after (x) dies | S16: =Assumptions!$B$7*S12 -> 45154.769
A17: 9 | B17: =IF(A17<Assumptions!$B$14,1,0) -> 1 | C17: =Assumptions!$B$5+A17 -> 74 | D17: =1-EXP(-Assumptions!$B$10-Assumptions!$B$11*Assumptions!$B$12^C17*(Assumptions!$B$12-1)/LN(Assumptions!$B$12)) -> 0.016440266 | E17: =Assumptions!$B$6+A17 -> 71 | F17: =1-EXP(-Assumptions!$B$10-Assumptions!$B$11*Assumptions!$B$12^E17*(Assumptions!$B$12-1)/LN(Assumptions!$B$12)) -> 0.011670038 | G17: =G16*(1-D16) -> 0.91592178 | H17: =H16*(1-F16) -> 0.9394767 | I17: =G17*H17 -> 0.86048717 | J17: =G17+H17-I17 -> 0.99491131 | K17: =(1+Assumptions!$B$9)^-A17 -> 0.64460892 | L17: =B17*K17*G17 -> 0.59041135 | M17: =B17*K17*H17 -> 0.60559506 | N17: =B17*K17*I17 -> 0.5546777 | O17: =B17*K17*J17 -> 0.6413287 | P17: =B17*I17*D17*(1-F17/2) -> 0.014064092 | R17: Probability that (x) dies first | S17: =SUM(P8:P78) -> 0.58596177
A18: 10 | B18: =IF(A18<Assumptions!$B$14,1,0) -> 1 | C18: =Assumptions!$B$5+A18 -> 75 | D18: =1-EXP(-Assumptions!$B$10-Assumptions!$B$11*Assumptions!$B$12^C18*(Assumptions!$B$12-1)/LN(Assumptions!$B$12)) -> 0.018433156 | E18: =Assumptions!$B$6+A18 -> 72 | F18: =1-EXP(-Assumptions!$B$10-Assumptions!$B$11*Assumptions!$B$12^E18*(Assumptions!$B$12-1)/LN(Assumptions!$B$12)) -> 0.013080677 | G18: =G17*(1-D17) -> 0.90086379 | H18: =H17*(1-F17) -> 0.92851297 | I18: =G18*H18 -> 0.83646371 | J18: =G18+H18-I18 -> 0.99291305 | K18: =(1+Assumptions!$B$9)^-A18 -> 0.61391325 | L18: =B18*K18*G18 -> 0.55305222 | M18: =B18*K18*H18 -> 0.57002642 | N18: =B18*K18*I18 -> 0.51351616 | O18: =B18*K18*J18 -> 0.60956248 | P18: =B18*I18*D18*(1-F18/2) -> 0.015317823 | R18: Check: joint + last survivor = x + y | S18: =IF(ABS(S10+S11-S8-S9)<0.000001,"OK","Mismatch") -> OK
A19: 11 | B19: =IF(A19<Assumptions!$B$14,1,0) -> 1 | C19: =Assumptions!$B$5+A19 -> 76 | D19: =1-EXP(-Assumptions!$B$10-Assumptions!$B$11*Assumptions!$B$12^C19*(Assumptions!$B$12-1)/LN(Assumptions!$B$12)) -> 0.020668344 | E19: =Assumptions!$B$6+A19 -> 73 | F19: =1-EXP(-Assumptions!$B$10-Assumptions!$B$11*Assumptions!$B$12^E19*(Assumptions!$B$12-1)/LN(Assumptions!$B$12)) -> 0.014663832 | G19: =G18*(1-D18) -> 0.88425802 | H19: =H18*(1-F18) -> 0.91636739 | I19: =G19*H19 -> 0.81030522 | J19: =G19+H19-I19 -> 0.9903202 | K19: =(1+Assumptions!$B$9)^-A19 -> 0.58467929 | L19: =B19*K19*G19 -> 0.51700735 | M19: =B19*K19*H19 -> 0.53578103 | N19: =B19*K19*I19 -> 0.47376868 | O19: =B19*K19*J19 -> 0.57901971 | P19: =B19*I19*D19*(1-F19/2) -> 0.016624875
A20: 12 | B20: =IF(A20<Assumptions!$B$14,1,0) -> 1 | C20: =Assumptions!$B$5+A20 -> 77 | D20: =1-EXP(-Assumptions!$B$10-Assumptions!$B$11*Assumptions!$B$12^C20*(Assumptions!$B$12-1)/LN(Assumptions!$B$12)) -> 0.023174621 | E20: =Assumptions!$B$6+A20 -> 74 | F20: =1-EXP(-Assumptions!$B$10-Assumptions!$B$11*Assumptions!$B$12^E20*(Assumptions!$B$12-1)/LN(Assumptions!$B$12)) -> 0.016440266 | G20: =G19*(1-D19) -> 0.86598187 | H20: =H19*(1-F19) -> 0.90292993 | I20: =G20*H20 -> 0.78192096 | J20: =G20+H20-I20 -> 0.98699085 | K20: =(1+Assumptions!$B$9)^-A20 -> 0.55683742 | L20: =B20*K20*G20 -> 0.48221111 | M20: =B20*K20*H20 -> 0.50278517 | N20: =B20*K20*I20 -> 0.43540285 | O20: =B20*K20*J20 -> 0.54959344 | P20: =B20*I20*D20*(1-F20/2) -> 0.017971767
A21: 13 | B21: =IF(A21<Assumptions!$B$14,1,0) -> 1 | C21: =Assumptions!$B$5+A21 -> 78 | D21: =1-EXP(-Assumptions!$B$10-Assumptions!$B$11*Assumptions!$B$12^C21*(Assumptions!$B$12-1)/LN(Assumptions!$B$12)) -> 0.02598402 | E21: =Assumptions!$B$6+A21 -> 75 | F21: =1-EXP(-Assumptions!$B$10-Assumptions!$B$11*Assumptions!$B$12^E21*(Assumptions!$B$12-1)/LN(Assumptions!$B$12)) -> 0.018433156 | G21: =G20*(1-D20) -> 0.84591307 | H21: =H20*(1-F20) -> 0.88808552 | I21: =G21*H21 -> 0.75124315 | J21: =G21+H21-I21 -> 0.98275544 | K21: =(1+Assumptions!$B$9)^-A21 -> 0.53032135 | L21: =B21*K21*G21 -> 0.44860576 | M21: =B21*K21*H21 -> 0.47097071 | N21: =B21*K21*I21 -> 0.39840028 | O21: =B21*K21*J21 -> 0.52117619 | P21: =B21*I21*D21*(1-F21/2) -> 0.019340406
A22: 14 | B22: =IF(A22<Assumptions!$B$14,1,0) -> 1 | C22: =Assumptions!$B$5+A22 -> 79 | D22: =1-EXP(-Assumptions!$B$10-Assumptions!$B$11*Assumptions!$B$12^C22*(Assumptions!$B$12-1)/LN(Assumptions!$B$12)) -> 0.029132141 | E22: =Assumptions!$B$6+A22 -> 76 | F22: =1-EXP(-Assumptions!$B$10-Assumptions!$B$11*Assumptions!$B$12^E22*(Assumptions!$B$12-1)/LN(Assumptions!$B$12)) -> 0.020668344 | G22: =G21*(1-D21) -> 0.82393285 | H22: =H21*(1-F21) -> 0.87171531 | I22: =G22*H22 -> 0.71823488 | J22: =G22+H22-I22 -> 0.97741328 | K22: =(1+Assumptions!$B$9)^-A22 -> 0.50506795 | L22: =B22*K22*G22 -> 0.41614208 | M22: =B22*K22*H22 -> 0.44027547 | N22: =B22*K22*I22 -> 0.36275742 | O22: =B22*K22*J22 -> 0.49366012 | P22: =B22*I22*D22*(1-F22/2) -> 0.02070749
A23: 15 | B23: =IF(A23<Assumptions!$B$14,1,0) -> 1 | C23: =Assumptions!$B$5+A23 -> 80 | D23: =1-EXP(-Assumptions!$B$10-Assumptions!$B$11*Assumptions!$B$12^C23*(Assumptions!$B$12-1)/LN(Assumptions!$B$12)) -> 0.032658484 | E23: =Assumptions!$B$6+A23 -> 77 | F23: =1-EXP(-Assumptions!$B$10-Assumptions!$B$11*Assumptions!$B$12^E23*(Assumptions!$B$12-1)/LN(Assumptions!$B$12)) -> 0.023174621 | G23: =G22*(1-D22) -> 0.79992992 | H23: =H22*(1-F22) -> 0.85369839 | I23: =G23*H23 -> 0.68289889 | J23: =G23+H23-I23 -> 0.97072943 | K23: =(1+Assumptions!$B$9)^-A23 -> 0.4810171 | L23: =B23*K23*G23 -> 0.38477997 | M23: =B23*K23*H23 -> 0.41064352 | N23: =B23*K23*I23 -> 0.32848604 | O23: =B23*K23*J23 -> 0.46693745 | P23: =B23*I23*D23*(1-F23/2) -> 0.022044017
A24: 16 | B24: =IF(A24<Assumptions!$B$14,1,0) -> 1 | C24: =Assumptions!$B$5+A24 -> 81 | D24: =1-EXP(-Assumptions!$B$10-Assumptions!$B$11*Assumptions!$B$12^C24*(Assumptions!$B$12-1)/LN(Assumptions!$B$12)) -> 0.036606808 | E24: =Assumptions!$B$6+A24 -> 78 | F24: =1-EXP(-Assumptions!$B$10-Assumptions!$B$11*Assumptions!$B$12^E24*(Assumptions!$B$12-1)/LN(Assumptions!$B$12)) -> 0.02598402 | G24: =G23*(1-D23) -> 0.77380542 | H24: =H23*(1-F23) -> 0.83391426 | I24: =G24*H24 -> 0.64528738 | J24: =G24+H24-I24 -> 0.96243231 | K24: =(1+Assumptions!$B$9)^-A24 -> 0.45811152 | L24: =B24*K24*G24 -> 0.35448918 | M24: =B24*K24*H24 -> 0.38202573 | N24: =B24*K24*I24 -> 0.29561358 | O24: =B24*K24*J24 -> 0.44090133 | P24: =B24*I24*D24*(1-F24/2) -> 0.023315015
A25: 17 | B25: =IF(A25<Assumptions!$B$14,1,0) -> 1 | C25: =Assumptions!$B$5+A25 -> 82 | D25: =1-EXP(-Assumptions!$B$10-Assumptions!$B$11*Assumptions!$B$12^C25*(Assumptions!$B$12-1)/LN(Assumptions!$B$12)) -> 0.04102549 | E25: =Assumptions!$B$6+A25 -> 79 | F25: =1-EXP(-Assumptions!$B$10-Assumptions!$B$11*Assumptions!$B$12^E25*(Assumptions!$B$12-1)/LN(Assumptions!$B$12)) -> 0.029132141 | G25: =G24*(1-D24) -> 0.74547888 | H25: =H24*(1-F24) -> 0.81224581 | I25: =G25*H25 -> 0.6055121 | J25: =G25+H25-I25 -> 0.95221259 | K25: =(1+Assumptions!$B$9)^-A25 -> 0.43629669 | L25: =B25*K25*G25 -> 0.32524996 | M25: =B25*K25*H25 -> 0.35438016 | N25: =B25*K25*I25 -> 0.26418292 | O25: =B25*K25*J25 -> 0.4154472 | P25: =B25*I25*D25*(1-F25/2) -> 0.024479588
A26: 18 | B26: =IF(A26<Assumptions!$B$14,1,0) -> 1 | C26: =Assumptions!$B$5+A26 -> 83 | D26: =1-EXP(-Assumptions!$B$10-Assumptions!$B$11*Assumptions!$B$12^C26*(Assumptions!$B$12-1)/LN(Assumptions!$B$12)) -> 0.045967901 | E26: =Assumptions!$B$6+A26 -> 80 | F26: =1-EXP(-Assumptions!$B$10-Assumptions!$B$11*Assumptions!$B$12^E26*(Assumptions!$B$12-1)/LN(Assumptions!$B$12)) -> 0.032658484 | G26: =G25*(1-D25) -> 0.71489524 | H26: =H25*(1-F25) -> 0.78858335 | I26: =G26*H26 -> 0.56375449 | J26: =G26+H26-I26 -> 0.93972411 | K26: =(1+Assumptions!$B$9)^-A26 -> 0.41552065 | L26: =B26*K26*G26 -> 0.29705374 | M26: =B26*K26*H26 -> 0.32767267 | N26: =B26*K26*I26 -> 0.23425163 | O26: =B26*K26*J26 -> 0.39047478 | P26: =B26*I26*D26*(1-F26/2) -> 0.025491445
A27: 19 | B27: =IF(A27<Assumptions!$B$14,1,0) -> 1 | C27: =Assumptions!$B$5+A27 -> 84 | D27: =1-EXP(-Assumptions!$B$10-Assumptions!$B$11*Assumptions!$B$12^C27*(Assumptions!$B$12-1)/LN(Assumptions!$B$12)) -> 0.051492772 | E27: =Assumptions!$B$6+A27 -> 81 | F27: =1-EXP(-Assumptions!$B$10-Assumptions!$B$11*Assumptions!$B$12^E27*(Assumptions!$B$12-1)/LN(Assumptions!$B$12)) -> 0.036606808 | G27: =G26*(1-D26) -> 0.68203301 | H27: =H26*(1-F26) -> 0.76282942 | I27: =G27*H27 -> 0.52027484 | J27: =G27+H27-I27 -> 0.92458758 | K27: =(1+Assumptions!$B$9)^-A27 -> 0.39573396 | L27: =B27*K27*G27 -> 0.26990362 | M27: =B27*K27*H27 -> 0.3018775 | N27: =B27*K27*I27 -> 0.20589042 | O27: =B27*K27*J27 -> 0.3658907 | P27: =B27*I27*D27*(1-F27/2) -> 0.026300038
A28: 20 | B28: =IF(A28<Assumptions!$B$14,1,0) -> 1 | C28: =Assumptions!$B$5+A28 -> 85 | D28: =1-EXP(-Assumptions!$B$10-Assumptions!$B$11*Assumptions!$B$12^C28*(Assumptions!$B$12-1)/LN(Assumptions!$B$12)) -> 0.057664543 | E28: =Assumptions!$B$6+A28 -> 82 | F28: =1-EXP(-Assumptions!$B$10-Assumptions!$B$11*Assumptions!$B$12^E28*(Assumptions!$B$12-1)/LN(Assumptions!$B$12)) -> 0.04102549 | G28: =G27*(1-D27) -> 0.64691324 | H28: =H27*(1-F27) -> 0.73490467 | I28: =G28*H28 -> 0.47541956 | J28: =G28+H28-I28 -> 0.90639835 | K28: =(1+Assumptions!$B$9)^-A28 -> 0.37688948 | L28: =B28*K28*G28 -> 0.2438148 | M28: =B28*K28*H28 -> 0.27697784 | N28: =B28*K28*I28 -> 0.17918063 | O28: =B28*K28*J28 -> 0.341612 | P28: =B28*I28*D28*(1-F28/2) -> 0.026852498
A29: 21 | B29: =IF(A29<Assumptions!$B$14,1,0) -> 1 | C29: =Assumptions!$B$5+A29 -> 86 | D29: =1-EXP(-Assumptions!$B$10-Assumptions!$B$11*Assumptions!$B$12^C29*(Assumptions!$B$12-1)/LN(Assumptions!$B$12)) -> 0.06455369 | E29: =Assumptions!$B$6+A29 -> 83 | F29: =1-EXP(-Assumptions!$B$10-Assumptions!$B$11*Assumptions!$B$12^E29*(Assumptions!$B$12-1)/LN(Assumptions!$B$12)) -> 0.045967901 | G29: =G28*(1-D28) -> 0.60960928 | H29: =H28*(1-F28) -> 0.70475484 | I29: =G29*H29 -> 0.42962509 | J29: =G29+H29-I29 -> 0.88473903 | K29: =(1+Assumptions!$B$9)^-A29 -> 0.35894236 | L29: =B29*K29*G29 -> 0.2188146 | M29: =B29*K29*H29 -> 0.25296637 | N29: =B29*K29*I29 -> 0.15421065 | O29: =B29*K29*J29 -> 0.31757032 | P29: =B29*I29*D29*(1-F29/2) -> 0.027096451
A30: 22 | B30: =IF(A30<Assumptions!$B$14,1,0) -> 1 | C30: =Assumptions!$B$5+A30 -> 87 | D30: =1-EXP(-Assumptions!$B$10-Assumptions!$B$11*Assumptions!$B$12^C30*(Assumptions!$B$12-1)/LN(Assumptions!$B$12)) -> 0.07223699 | E30: =Assumptions!$B$6+A30 -> 84 | F30: =1-EXP(-Assumptions!$B$10-Assumptions!$B$11*Assumptions!$B$12^E30*(Assumptions!$B$12-1)/LN(Assumptions!$B$12)) -> 0.051492772 | G30: =G29*(1-D29) -> 0.57025675 | H30: =H29*(1-F29) -> 0.67235874 | I30: =G30*H30 -> 0.38341711 | J30: =G30+H30-I30 -> 0.85919838 | K30: =(1+Assumptions!$B$9)^-A30 -> 0.34184987 | L30: =B30*K30*G30 -> 0.1949422 | M30: =B30*K30*H30 -> 0.22984575 | N30: =B30*K30*I30 -> 0.13107109 | O30: =B30*K30*J30 -> 0.29371686 | P30: =B30*I30*D30*(1-F30/2) -> 0.026983803
... A78: 70 | B78: =IF(A78<Assumptions!$B$14,1,0) -> 0 | C78: =Assumptions!$B$5+A78 -> 135 | D78: =1-EXP(-Assumptions!$B$10-Assumptions!$B$11*Assumptions!$B$12^C78*(Assumptions!$B$12-1)/LN(Assumptions!$B$12)) -> 1 | E78: =Assumptions!$B$6+A78 -> 132 | F78: =1-EXP(-Assumptions!$B$10-Assumptions!$B$11*Assumptions!$B$12^E78*(Assumptions!$B$12-1)/LN(Assumptions!$B$12)) -> 0.99999944 | G78: =G77*(1-D77) -> 2.6946323e-72 | H78: =H77*(1-F77) -> 3.9645503e-51 | I78: =G78*H78 -> 1.0683005e-122 | J78: =G78+H78-I78 -> 3.9645503e-51 | K78: =(1+Assumptions!$B$9)^-A78 -> 0.032866168 | L78: =B78*K78*G78 -> 0 | M78: =B78*K78*H78 -> 0 | N78: =B78*K78*I78 -> 0 | O78: =B78*K78*J78 -> 0 | P78: =B78*I78*D78*(1-F78/2) -> 0

Sheet Cross-check
A1: R calculator vs Excel
A2: R values were read off the calculator's Chapter 3 tab at the default assumptions (ages 65 and 62, $20,000, 60%, 5%). If you change the assumptions, re-enter the R values from the app.
A4: Item | B4: R calculator | C4: Excel | D4: R minus Excel
A5: Cost of a joint and survivor pension | B5: 286716.9 | C5: ='Life table'!S13 -> 286716.9 | D5: =B5-C5 -> 0.0031489934
A6: Cost if income continues in full to the survivor | B6: 316150.57 | C6: ='Life table'!S14 -> 316150.57 | D6: =B6-C6 -> 0.00045859168
A7: Cost if income stops at the first death | B7: 242566.39 | C7: ='Life table'!S15 -> 242566.39 | D7: =B7-C7 -> 0.0021845959
A8: Cost of income to (y) only after (x) dies | B8: 45154.77 | C8: ='Life table'!S16 -> 45154.769 | D8: =B8-C8 -> 0.0012134534
A9: Annuity factor, x | B9: 13.5498 | C9: ='Life table'!S8 -> 13.54979 | D9: =B9-C9 -> 9.9622569e-06
A10: Annuity factor, y | B10: 14.3861 | C10: ='Life table'!S9 -> 14.386058 | D10: =B10-C10 -> 4.2169902e-05
A11: Annuity factor, joint life | B11: 12.1283 | C11: ='Life table'!S10 -> 12.128319 | D11: =B11-C11 -> -1.939077e-05
A12: Annuity factor, last survivor | B12: 15.8075 | C12: ='Life table'!S11 -> 15.807528 | D12: =B12-C12 -> -2.847707e-05
A14: R and Excel agree (to the rounding shown in the app)? | B14: =IF(AND(ABS(D5)<0.01,ABS(D6)<0.01,ABS(D7)<0.01,ABS(D8)<0.01,ABS(D9)<0.0001,ABS(D10)<0.0001,ABS(D11)<0.0001,ABS(D12)<0.0001),"Yes","No: check assumptions match the app") -> Yes
A16: Published SOA Standard Ultimate Life Table: annuity-due at age 65, 5% | B16: 13.5498 | C16: ='Life table'!S8 -> 13.54979 | D16: =B16-C16 -> 9.9622569e-06

Sheet Experience
A1: Couples study from the SQL experience data
A2: Values below are the SQL couples study: 20,000 simulated couples aged 65 and 62, followed for 30 years (seed 2026). The model uses the Life table sheet.
A4: Year | B4: Both alive at start | C4: At least one alive at start | D4: (x) dies first | E4: (y) dies first | F4: Both alive: observed | G4: Both alive: model | H4: At least one alive: observed | I4: At least one alive: model | K4: (x) dies first within 30 years
A5: 1 | B5: 20000 | C5: 20000 | D5: 109 | E5: 64 | F5: =IF($B$5>0,B5/$B$5,"") -> 1 | G5: ='Life table'!I8 -> 1 | H5: =IF($B$5>0,C5/$B$5,"") -> 1 | I5: ='Life table'!J8 -> 1 | K5: Measure | L5: Observed | M5: Model
A6: 2 | B6: 19827 | C6: 20000 | D6: 135 | E6: 95 | F6: =IF($B$5>0,B6/$B$5,"") -> 0.99135 | G6: ='Life table'!I9 -> 0.98987679 | H6: =IF($B$5>0,C6/$B$5,"") -> 1 | I6: ='Life table'!J9 -> 0.99997496 | K6: Proportion of couples | L6: =IF(B5>0,SUM(D5:D34)/B5,"") -> 0.5368 | M6: =SUMPRODUCT(('Life table'!A8:A78<30)*'Life table'!I8:I78*'Life table'!D8:D78*(1-'Life table'!F8:F78/2)) -> 0.54030731
A7: 3 | B7: 19597 | C7: 19998 | D7: 145 | E7: 98 | F7: =IF($B$5>0,B7/$B$5,"") -> 0.97985 | G7: ='Life table'!I10 -> 0.97867397 | H7: =IF($B$5>0,C7/$B$5,"") -> 0.9999 | I7: ='Life table'!J10 -> 0.99988826
A8: 4 | B8: 19354 | C8: 19997 | D8: 173 | E8: 118 | F8: =IF($B$5>0,B8/$B$5,"") -> 0.9677 | G8: ='Life table'!I11 -> 0.96628599 | H8: =IF($B$5>0,C8/$B$5,"") -> 0.99985 | I8: ='Life table'!J11 -> 0.999719
A9: 5 | B9: 19063 | C9: 19994 | D9: 193 | E9: 116 | F9: =IF($B$5>0,B9/$B$5,"") -> 0.95315 | G9: ='Life table'!I12 -> 0.95260096 | H9: =IF($B$5>0,C9/$B$5,"") -> 0.9997 | I9: ='Life table'!J12 -> 0.99944071
A10: 6 | B10: 18754 | C10: 19987 | D10: 216 | E10: 135 | F10: =IF($B$5>0,B10/$B$5,"") -> 0.9377 | G10: ='Life table'!I13 -> 0.93750135 | H10: =IF($B$5>0,C10/$B$5,"") -> 0.99935 | I10: ='Life table'!J13 -> 0.99902005
A11: 7 | B11: 18403 | C11: 19975 | D11: 221 | E11: 155 | F11: =IF($B$5>0,B11/$B$5,"") -> 0.92015 | G11: ='Life table'!I14 -> 0.92086514 | H11: =IF($B$5>0,C11/$B$5,"") -> 0.99875 | I11: ='Life table'!J14 -> 0.99841525
A12: 8 | B12: 18027 | C12: 19959 | D12: 217 | E12: 146 | F12: =IF($B$5>0,B12/$B$5,"") -> 0.90135 | G12: ='Life table'!I15 -> 0.90256742 | H12: =IF($B$5>0,C12/$B$5,"") -> 0.99795 | I12: ='Life table'!J15 -> 0.99757429
A13: 9 | B13: 17664 | C13: 19944 | D13: 241 | E13: 199 | F13: =IF($B$5>0,B13/$B$5,"") -> 0.8832 | G13: ='Life table'!I16 -> 0.88248257 | H13: =IF($B$5>0,C13/$B$5,"") -> 0.9972 | I13: ='Life table'!J16 -> 0.99643273
A14: 10 | B14: 17224 | C14: 19922 | D14: 299 | E14: 201 | F14: =IF($B$5>0,B14/$B$5,"") -> 0.8612 | G14: ='Life table'!I17 -> 0.86048717 | H14: =IF($B$5>0,C14/$B$5,"") -> 0.9961 | I14: ='Life table'!J17 -> 0.99491131
A15: 11 | B15: 16724 | C15: 19880 | D15: 321 | E15: 221 | F15: =IF($B$5>0,B15/$B$5,"") -> 0.8362 | G15: ='Life table'!I18 -> 0.83646371 | H15: =IF($B$5>0,C15/$B$5,"") -> 0.994 | I15: ='Life table'!J18 -> 0.99291305
A16: 12 | B16: 16182 | C16: 19818 | D16: 345 | E16: 229 | F16: =IF($B$5>0,B16/$B$5,"") -> 0.8091 | G16: ='Life table'!I19 -> 0.81030522 | H16: =IF($B$5>0,C16/$B$5,"") -> 0.9909 | I16: ='Life table'!J19 -> 0.9903202
A17: 13 | B17: 15608 | C17: 19761 | D17: 349 | E17: 264 | F17: =IF($B$5>0,B17/$B$5,"") -> 0.7804 | G17: ='Life table'!I20 -> 0.78192096 | H17: =IF($B$5>0,C17/$B$5,"") -> 0.98805 | I17: ='Life table'!J20 -> 0.98699085
A18: 14 | B18: 14995 | C18: 19679 | D18: 381 | E18: 287 | F18: =IF($B$5>0,B18/$B$5,"") -> 0.74975 | G18: ='Life table'!I21 -> 0.75124315 | H18: =IF($B$5>0,C18/$B$5,"") -> 0.98395 | I18: ='Life table'!J21 -> 0.98275544
... A34: 30 | B34: 2139 | C34: 11070 | D34: 312 | E34: 231 | F34: =IF($B$5>0,B34/$B$5,"") -> 0.10695 | G34: ='Life table'!I37 -> 0.10403446 | H34: =IF($B$5>0,C34/$B$5,"") -> 0.5535 | I34: ='Life table'!J37 -> 0.55339275
